file_primitives/__init__.py
file_primitives/delete_path.py
file_primitives/ensure_dir.py
file_primitives/read_file.py
file_primitives/write_file.py
file_primitives-0.2.0.dist-info/METADATA
file_primitives-0.2.0.dist-info/WHEEL
file_primitives-0.2.0.dist-info/licenses/LICENSE
file_primitives-0.2.0.dist-info/RECORD
