Metadata-Version: 2.4
Name: file-primitives
Version: 0.2.0
Summary: File primitives for Python
Author-email: Mark Lidenberg <marklidenberg@gmail.com>
License: MIT
License-File: LICENSE
Classifier: Intended Audience :: Developers
Classifier: License :: OSI Approved :: MIT License
Classifier: Programming Language :: Python :: 3
Classifier: Programming Language :: Python :: 3.8
Classifier: Programming Language :: Python :: 3.9
Classifier: Programming Language :: Python :: 3.10
Classifier: Programming Language :: Python :: 3.11
Classifier: Programming Language :: Python :: 3.12
Classifier: Programming Language :: Python :: 3.13
Requires-Python: >=3.8
Provides-Extra: dev
Requires-Dist: better-exceptions>=0.3.3; extra == 'dev'
Requires-Dist: build>=1.2.2.post1; extra == 'dev'
Requires-Dist: dony>=0.2.1; extra == 'dev'
Requires-Dist: load-dotenv>=0.1.0; extra == 'dev'
Requires-Dist: questionary>=2.1.0; extra == 'dev'
Requires-Dist: twine>=6.1.0; extra == 'dev'
